{
  "document_metadata": {
    "document_number": "2014035116",
    "title": "2014035116 20 DECEMBRE 2013. - Arrêté du Gouvernement flamand relatif à la redistribution du crédit provisionnel inscrit à l'article budgétaire CB0/1CB-G-2-Z/PR du budget général des dépenses de la Communauté flamande pour l'année budgétaire 2013",
    "publication_date": "2014-02-06",
    "source": "Autorité flamande",
    "page_number": 10753,
    "dossier_number": "2013-12-20/47",
    "effective_date": "2013-01-01",
    "language": "fr",
    "document_type": "arrete",
    "status": "active",
    "version_info": {
      "archived_versions_count": 0,
      "archived_versions_url": "",
      "execution_orders_count": 0,
      "execution_orders_url": ""
    },
    "official_justel_url": "https://www.ejustice.just.fgov.be/eli/arrete/2013/12/20/2014035116/justel",
    "official_publication_pdf_url": "https://www.ejustice.just.fgov.be/mopdf/2014/02/06_2.pdf#Page55",
    "consolidated_pdf_url": ""
  },
  "document_hierarchy": [
    {
      "type": "article",
      "label": "Art. 1er",
      "metadata": {
        "article_range": "1er",
        "rank": 5
      },
      "article_content": {
        "article_number": "1er",
        "anchor_id": "art_1er",
        "content": {
          "main_text": ". Les crédits inscrits aux articles budgétaires du budget général des dépenses de la Communauté flamande pour l'année budgétaire 2013 sont redistribués conformément au tableau ci-dessous :  \n (en milliers d'euros) \n  \n  | article budgétaire | allocation de base | type de crédit | de | vers |  |  |  | CE | CL | CE | CL   \n   | CB0/1CB-G-2-Z/PR | CB0 CB024 0100 | CE | 13.282 |  |  |  |  |  | CL |  | 13.282 |  |  | BFO/1BF-C-2-A/WT | BF0 BF516 7200 | CE |  |  | 13.282 |  |  |  | CL |  |  |  | 13.282 | total | 13.282 | 13.282 | 13.282 | 13.282  \nRègles de redistribution entre des types de crédit :  \n (1) CL = crédit corrélatif (CE/CL);  \n (2) CE = AUT.",
          "numbered_provisions": []
        }
      },
      "footnotes": [],
      "footnote_references": []
    },
    {
      "type": "article",
      "label": "Art. 2",
      "metadata": {
        "article_range": "2",
        "rank": 5
      },
      "article_content": {
        "article_number": "2",
        "anchor_id": "art_2",
        "content": {
          "main_text": "Une copie du présent arrêté est transmise, à titre d'information, au Parlement flamand, à la Cour des Comptes et au Département des Finances et du Budget.  \n  \n**ARTICLE**[Art.] 3\\. Le Ministre flamand ayant les finances et le budget dans ses attributions est chargé de l'exécution du présent arrêté.  \n  \n\n[11A] ## Signatures [11B]\n\n   Bruxelles, le 20 décembre 2013.  \nLe Ministre-Président du Gouvernement flamand,  \nK. PEETERS  \nLe Ministre flamand des Finances, du Budget, de l'Emploi, de l'Aménagement du Territoire et des Sports,  \nPh. MUYTERS \n\n[9A] ## Préambule [9B]\n\n   Le Gouvernement flamand,  \n   Vu le décret du 8 juillet 2011 réglant le budget, la comptabilité, l'attribution de subventions et le contrôle de leur utilisation, et le contrôle par la Cour des Comptes;  \n   Vu le décret du 21 décembre 2012 contenant le budget général des dépenses de la Communauté flamande pour l'année budgétaire 2013, notamment l'article 56;  \n   Vu le décret du 28 juin 2013 ajustant le budget général des dépenses de la Communauté flamande pour l'année budgétaire 2013;  \n   Vu l'accord du Ministre flamand chargé du budget, donné le 20 décembre 2013;  \n   Sur la proposition du Ministre flamand des Finances et du Budget;  \n   Après délibération,  \n   Arrête : \n\n[5A] [6A] ## Lien [6B]s [5B]\n\n<https://www.ejustice.just.fgov.be/eli/arrete/2013/12/20/2014035116/justel> Copier le lien [Image de la publication officielle](https://www.ejustice.just.fgov.be/mopdf/2014/02/06_2.pdf#Page55) Informations générales\n\n  * [Conditions d'utilisation](https://www.ejustice.just.fgov.be/img_2024/pdf/GebruiksvoorwaardenFR.pdf)\n\nLiens utiles\n\n  * [SPF Justice](https://justitie.belgium.be/fr)\n  * [Ministère Public](https://www.om-mp.be/fr)\n  * [Cours & tribunaux](https://www.rechtbanken-tribunaux.be/fr)\n  * [Cours de cassation](https://justice.belgium.be/fr/ordre_judiciaire/cours_et_tribunaux/cour_de_cassation)\n\nCopyright © 2024 Service Public Fédéral Belge",
          "numbered_provisions": []
        }
      },
      "footnotes": [],
      "footnote_references": []
    }
  ],
  "references": {
    "modifies": [],
    "modified_by": []
  },
  "external_links": {
    "official_links": [],
    "parliamentary_work": []
  },
  "extraction_metadata": {
    "extraction_date": "2025-07-12T13:12:32.541732",
    "source_file": "2014035116.md",
    "sections_included": [
      "document_metadata",
      "document_hierarchy",
      "references"
    ],
    "sections_excluded": [
      "articles",
      "legal_references",
      "modification_history"
    ],
    "completeness_flags": {
      "all_articles_extracted": true,
      "footnotes_linked": true,
      "hierarchical_structure_complete": true,
      "metadata_complete": true,
      "is_minimal_document": false
    }
  }
}